pyclier_demo/__init__.py
pyclier_demo/__main__.py
pyclier_demo/cli.py
pyclier_demo/config.py
pyclier_demo-0.1.0.dist-info/METADATA
pyclier_demo-0.1.0.dist-info/WHEEL
pyclier_demo-0.1.0.dist-info/entry_points.txt
pyclier_demo-0.1.0.dist-info/top_level.txt
pyclier_demo-0.1.0.dist-info/RECORD
