Metadata-Version: 2.1
Name: pyclier-demo
Version: 0.1.0
Summary: Pyclier Demo.
Home-page: https://github.com/zhangxianbing/pyclier-demo
Author: zhangxianbing
Author-email: zhangxianbing09@163.com
License: UNKNOWN
Platform: UNKNOWN
Requires-Python: >=3.6
Requires-Dist: setuptools (>=40.6.2)
Requires-Dist: appdirs (>=1.4.4)
Requires-Dist: rich (>=10.1.0)
Requires-Dist: PyYAML (>=5.4.1)
Requires-Dist: pyclier (>=0.1.2)
